bodywork/__init__.py
bodywork/config.py
bodywork/constants.py
bodywork/exceptions.py
bodywork/git.py
bodywork/logs.py
bodywork/stage_execution.py
bodywork/workflow_execution.py
bodywork/cli/__init__.py
bodywork/cli/cli.py
bodywork/cli/secrets.py
bodywork/cli/service_deployments.py
bodywork/cli/setup_namespace.py
bodywork/cli/workflow_jobs.py
bodywork/k8s/__init__.py
bodywork/k8s/auth.py
bodywork/k8s/batch_jobs.py
bodywork/k8s/namespaces.py
bodywork/k8s/pod_logs.py
bodywork/k8s/secrets.py
bodywork/k8s/service_deployments.py
bodywork/k8s/utils.py
bodywork/k8s/workflow_jobs.py
bodywork-2.1.3.dist-info/LICENSE
bodywork-2.1.3.dist-info/METADATA
bodywork-2.1.3.dist-info/WHEEL
bodywork-2.1.3.dist-info/entry_points.txt
bodywork-2.1.3.dist-info/top_level.txt
bodywork-2.1.3.dist-info/zip-safe
bodywork-2.1.3.dist-info/RECORD
