Metadata-Version: 2.1
Name: bodywork
Version: 2.1.3
Summary: Deploy machine learning to Kubernetes - MLOps accelerated.
Home-page: https://www.bodyworkml.com
Author: Bodywork Machine Learning Ltd.
Author-email: info@bodyworkml.com
License: AGPL 3.0
Project-URL: Source, https://github.com/bodywork-ml/bodywork-core
Project-URL: Documentation, https://bodywork.readthedocs.io/en/latest/
Platform: UNKNOWN
Classifier: Development Status :: 5 - Production/Stable
Classifier: License :: OSI Approved :: GNU Affero General Public License v3
Classifier: Programming Language :: Python :: 3.7
Classifier: Programming Language :: Python :: 3.8
Requires-Python: >=3.7.*
License-File: LICENSE
Requires-Dist: Cerberus (==1.3.2)
Requires-Dist: kubernetes (==17.17.0)
Requires-Dist: PyYAML (==5.4.1)
Requires-Dist: requests (>=2.25.0)
Provides-Extra: dev
Requires-Dist: pytest (==5.4.3) ; extra == 'dev'
Requires-Dist: pytest-cov (==2.10.0) ; extra == 'dev'
Requires-Dist: mypy (==0.782) ; extra == 'dev'
Requires-Dist: flake8 (==3.8.3) ; extra == 'dev'
Requires-Dist: tox (==3.20.1) ; extra == 'dev'
Requires-Dist: twine (==3.2.0) ; extra == 'dev'
Requires-Dist: wheel (==0.34.2) ; extra == 'dev'
